LICENSE
MANIFEST.in
README.md
package.json
setup.py
datepicker_by_inclusion/DatepickerByInclusion.py
datepicker_by_inclusion/__init__.py
datepicker_by_inclusion/_imports_.py
datepicker_by_inclusion/datepicker_by_inclusion.min.js
datepicker_by_inclusion/datepicker_by_inclusion.min.js.map
datepicker_by_inclusion/metadata.json
datepicker_by_inclusion/package-info.json
datepicker_by_inclusion.egg-info/PKG-INFO
datepicker_by_inclusion.egg-info/SOURCES.txt
datepicker_by_inclusion.egg-info/dependency_links.txt
datepicker_by_inclusion.egg-info/top_level.txt