Metadata-Version: 1.1
Name: datepicker-by-inclusion
Version: 0.0.2
Summary: Adapts react-datepicker for use in Dash, specifically to bring in the includeDates functionality
Home-page: UNKNOWN
Author: John Choiniere <john.choiniere@gmail.com>
Author-email: UNKNOWN
License: MIT
Platform: UNKNOWN
Classifier: Framework :: Dash
